heart/__init__.py
heart/keyword_extractor.py
heart/pattern_builder.py
heart/pattern_matcher.py
heart/summary_generator.py
heart/text_reader.py
heartt-1.0.2.dist-info/METADATA
heartt-1.0.2.dist-info/WHEEL
heartt-1.0.2.dist-info/top_level.txt
heartt-1.0.2.dist-info/RECORD
