Metadata-Version: 2.1
Name: heartt
Version: 1.0.2
Summary: This is a Python algorithm for generating text summaries.
Home-page: https://github.com/Liu-from-the-production-team/Heart-Toolkit
Author: LiuZhenming
Author-email: 2124619132@qq.com
License: GUN 3.0
Classifier: Programming Language :: Python :: 3
Classifier: License :: OSI Approved :: MIT License
Classifier: Operating System :: OS Independent
Requires-Python: >=3.10.9
Requires-Dist: nltk
Requires-Dist: jieba
